xlpd/__init__.py
xlpd/__init__.pyi
xlpd/_core.cpython-312-x86_64-linux-gnu.so
xlpd/cli.py
xlpd-0.1.14.dist-info/METADATA
xlpd-0.1.14.dist-info/WHEEL
xlpd-0.1.14.dist-info/entry_points.txt
xlpd-0.1.14.dist-info/RECORD
