Metadata-Version: 2.2
Name: xlpd
Version: 0.1.14
Summary: A minimal example package (with pybind11)
Author-Email: Yinchu Xia <sales@pytorchsoft.com>
Classifier: Development Status :: 4 - Beta
Classifier: License :: OSI Approved :: MIT License
Classifier: Programming Language :: Python :: 3.12
Classifier: Programming Language :: Python :: 3.13
Requires-Python: >=3.9
